marioscrawler.py
setup.py
mariosCrawler.egg-info/PKG-INFO
mariosCrawler.egg-info/SOURCES.txt
mariosCrawler.egg-info/dependency_links.txt
mariosCrawler.egg-info/requires.txt
mariosCrawler.egg-info/top_level.txt