Metadata-Version: 1.0
Name: mariosCrawler
Version: 1.0
Summary: MSWL Development and tools project
Home-page: UNKNOWN
Author: Mario Gallegos
Author-email: mgallegos76@gmail.com
License: GPLv3
Platform: UNKNOWN
